odoo10_addon_l10n_ch_import_winbiz-10.0.1.0.0-py2.7-nspkg.pth
odoo/addons/l10n_ch_import_winbiz/README.rst
odoo/addons/l10n_ch_import_winbiz/__init__.py
odoo/addons/l10n_ch_import_winbiz/__manifest__.py
odoo/addons/l10n_ch_import_winbiz/i18n/am.po
odoo/addons/l10n_ch_import_winbiz/i18n/ca.po
odoo/addons/l10n_ch_import_winbiz/i18n/de.po
odoo/addons/l10n_ch_import_winbiz/i18n/el_GR.po
odoo/addons/l10n_ch_import_winbiz/i18n/es.po
odoo/addons/l10n_ch_import_winbiz/i18n/es_ES.po
odoo/addons/l10n_ch_import_winbiz/i18n/fi.po
odoo/addons/l10n_ch_import_winbiz/i18n/fr.po
odoo/addons/l10n_ch_import_winbiz/i18n/gl.po
odoo/addons/l10n_ch_import_winbiz/i18n/it.po
odoo/addons/l10n_ch_import_winbiz/i18n/l10n_ch_import_winbiz.pot
odoo/addons/l10n_ch_import_winbiz/i18n/nb_NO.po
odoo/addons/l10n_ch_import_winbiz/i18n/nl.po
odoo/addons/l10n_ch_import_winbiz/i18n/pt.po
odoo/addons/l10n_ch_import_winbiz/i18n/pt_BR.po
odoo/addons/l10n_ch_import_winbiz/i18n/pt_PT.po
odoo/addons/l10n_ch_import_winbiz/i18n/sl.po
odoo/addons/l10n_ch_import_winbiz/i18n/tr.po
odoo/addons/l10n_ch_import_winbiz/models/__init__.py
odoo/addons/l10n_ch_import_winbiz/models/account_journal.py
odoo/addons/l10n_ch_import_winbiz/security/security.xml
odoo/addons/l10n_ch_import_winbiz/static/description/icon.png
odoo/addons/l10n_ch_import_winbiz/tests/__init__.py
odoo/addons/l10n_ch_import_winbiz/tests/golden-output.txt
odoo/addons/l10n_ch_import_winbiz/tests/input.attribute-oriented.raw.xml
odoo/addons/l10n_ch_import_winbiz/tests/input.attribute-oriented.xml
odoo/addons/l10n_ch_import_winbiz/tests/input.element-oriented.xml
odoo/addons/l10n_ch_import_winbiz/tests/input.xls
odoo/addons/l10n_ch_import_winbiz/tests/test_import.py
odoo/addons/l10n_ch_import_winbiz/utils/__init__.py
odoo/addons/l10n_ch_import_winbiz/utils/importers.py
odoo/addons/l10n_ch_import_winbiz/views/account_journal_view.xml
odoo/addons/l10n_ch_import_winbiz/views/menu.xml
odoo10_addon_l10n_ch_import_winbiz-10.0.1.0.0.dist-info/DESCRIPTION.rst
odoo10_addon_l10n_ch_import_winbiz-10.0.1.0.0.dist-info/METADATA
odoo10_addon_l10n_ch_import_winbiz-10.0.1.0.0.dist-info/RECORD
odoo10_addon_l10n_ch_import_winbiz-10.0.1.0.0.dist-info/WHEEL
odoo10_addon_l10n_ch_import_winbiz-10.0.1.0.0.dist-info/metadata.json
odoo10_addon_l10n_ch_import_winbiz-10.0.1.0.0.dist-info/namespace_packages.txt
odoo10_addon_l10n_ch_import_winbiz-10.0.1.0.0.dist-info/top_level.txt
